cservice/__init__.py
cservice/demonizers.py
cservice-0.9.dist-info/METADATA
cservice-0.9.dist-info/WHEEL
cservice-0.9.dist-info/top_level.txt
cservice-0.9.dist-info/RECORD
